{
  "hash": "0123516e021aa80a16d654a3cf5c6b7e",
  "result": {
    "markdown": "---\ntitle: \"Lord Howe Island Group\"\ndescription: \"Post description\"\nimage: site_64217.png\ntitle-block-style: none\n---\n\n\n\n```{=html}\n<style>\n#title-block-header {\n    margin-block-end: 1rem;\n    position: relative;\n    margin-top: -1px;\n    display: none;\n}\n</style>\n```\n\n\n::: {.grid}\n::: {.g-col-5}\n<br>\n\n::: {.cell}\n::: {.cell-output-display}\n```{=html}\n<div id=\"htmlwidget-1ea26b651afa0a297039\" style=\"width:100%;height:193px;\" class=\"leaflet html-widget\"></div>\n<script type=\"application/json\" data-for=\"htmlwidget-1ea26b651afa0a297039\">{\"x\":{\"options\":{\"crs\":{\"crsClass\":\"L.CRS.EPSG3857\",\"code\":null,\"proj4def\":null,\"projectedBounds\":null,\"options\":{}}},\"calls\":[{\"method\":\"addTiles\",\"args\":[\"https://{s}.tile.openstreetmap.org/{z}/{x}/{y}.png\",null,null,{\"minZoom\":0,\"maxZoom\":18,\"tileSize\":256,\"subdomains\":\"abc\",\"errorTileUrl\":\"\",\"tms\":false,\"noWrap\":false,\"zoomOffset\":0,\"zoomReverse\":false,\"opacity\":1,\"zIndex\":1,\"detectRetina\":false,\"attribution\":\"&copy; <a href=\\\"https://openstreetmap.org/copyright/\\\">OpenStreetMap<\\/a>,  <a href=\\\"https://opendatacommons.org/licenses/odbl/\\\">ODbL<\\/a>\"}]},{\"method\":\"addPolygons\",\"args\":[[[[{\"lng\":[159.0168825980001,159.00098,159.0009790270001,159.0009735100001,159.0009713970001,159.0009700000001,159.3343000000001,159.3343000000001,159.334300007,159.3343000000001,159.0168825980001],\"lat\":[-31.83168952299997,-31.83168999999998,-31.79120621599998,-31.56125767499998,-31.47328139999996,-31.41501999999997,-31.41501999999997,-31.46664762199998,-31.76804687099997,-31.83167999999995,-31.83168952299997]}]]],null,null,{\"interactive\":true,\"className\":\"\",\"stroke\":true,\"color\":\"#03F\",\"weight\":5,\"opacity\":0.5,\"fill\":true,\"fillColor\":\"#03F\",\"fillOpacity\":0.2,\"smoothFactor\":1,\"noClip\":false},null,null,\"Lord Howe Island Group\",{\"interactive\":false,\"permanent\":false,\"direction\":\"auto\",\"opacity\":1,\"offset\":[0,0],\"textsize\":\"10px\",\"textOnly\":false,\"className\":\"\",\"sticky\":true},null]}],\"limits\":{\"lat\":[-31.83168999999998,-31.41501999999997],\"lng\":[159.0009700000001,159.334300007]}},\"evals\":[],\"jsHooks\":[]}</script>\n```\n:::\n:::\n\n:::\n::: {.g-col-7}\n## Lord Howe Island Group\n\nCountry/region: **Australia**\n\nApproximate area: **1461**\n\nMean temperature over the year (2021): 21.4 °C\n:::\n:::\n\n## Temperature profile\n\nHow is temperature varying in the sites? Data extracted from the Global Ocean OSTIA Sea Surface Temperature and Sea Ice Analysis for the period of 1992 to 2021.\n\n\n::: {.cell}\n::: {.cell-output-display}\n```{=html}\n<div class=\"dygraphs html-widget html-fill-item\" id=\"htmlwidget-32f2a3ad593530654363\" style=\"width:100%;height:464px;\"></div>\n<script type=\"application/json\" data-for=\"htmlwidget-32f2a3ad593530654363\">{\"x\":{\"attrs\":{\"axes\":{\"x\":{\"pixelsPerLabel\":60,\"drawAxis\":true},\"y\":{\"drawAxis\":true}},\"series\":{\"Lord Howe Island Group\":{\"axis\":\"y\"}},\"colors\":[\"#1F9C87\"],\"title\":\"Mean monthly temperature\",\"labels\":[\"month\",\"date\",\"Lord Howe Island Group\"],\"legend\":\"auto\",\"retainDateWindow\":false,\"customBars\":true,\"stackedGraph\":false,\"fillGraph\":false,\"fillAlpha\":0.1,\"stepPlot\":false,\"drawPoints\":false,\"pointSize\":1,\"drawGapEdgePoints\":false,\"connectSeparatedPoints\":false,\"strokeWidth\":1,\"strokeBorderColor\":\"white\",\"colorValue\":0.5,\"colorSaturation\":1,\"includeZero\":false,\"drawAxesAtZero\":false,\"logscale\":false,\"axisTickSize\":3,\"axisLineColor\":\"black\",\"axisLineWidth\":0.3,\"axisLabelColor\":\"black\",\"axisLabelFontSize\":14,\"axisLabelWidth\":60,\"drawGrid\":false,\"gridLineWidth\":0.3,\"rightGap\":5,\"digitsAfterDecimal\":2,\"labelsKMB\":false,\"labelsKMG2\":false,\"labelsUTC\":true,\"maxNumberWidth\":6,\"animatedZooms\":false,\"mobileDisableYTouch\":true,\"disableZoom\":false,\"ylabel\":\"Temperature (°C)\",\"showRangeSelector\":true,\"rangeSelectorHeight\":40,\"rangeSelectorPlotFillColor\":\"#D6D6D6\",\"rangeSelectorPlotStrokeColor\":\"\",\"interactionModel\":\"Dygraph.Interaction.defaultModel\",\"highlightCircleSize\":5,\"highlightSeriesBackgroundAlpha\":0.2,\"highlightSeriesOpts\":{\"strokeWidth\":2},\"hideOverlayOnMouseOut\":false},\"scale\":\"monthly\",\"group\":\"sst_mon\",\"annotations\":[],\"shadings\":[],\"events\":[],\"format\":\"date\",\"data\":[[\"1992-01-01T00:00:00.000Z\",\"1992-02-01T00:00:00.000Z\",\"1992-03-01T00:00:00.000Z\",\"1992-04-01T00:00:00.000Z\",\"1992-05-01T00:00:00.000Z\",\"1992-06-01T00:00:00.000Z\",\"1992-07-01T00:00:00.000Z\",\"1992-08-01T00:00:00.000Z\",\"1992-09-01T00:00:00.000Z\",\"1992-10-01T00:00:00.000Z\",\"1992-11-01T00:00:00.000Z\",\"1992-12-01T00:00:00.000Z\",\"1993-01-01T00:00:00.000Z\",\"1993-02-01T00:00:00.000Z\",\"1993-03-01T00:00:00.000Z\",\"1993-04-01T00:00:00.000Z\",\"1993-05-01T00:00:00.000Z\",\"1993-06-01T00:00:00.000Z\",\"1993-07-01T00:00:00.000Z\",\"1993-08-01T00:00:00.000Z\",\"1993-09-01T00:00:00.000Z\",\"1993-10-01T00:00:00.000Z\",\"1993-11-01T00:00:00.000Z\",\"1993-12-01T00:00:00.000Z\",\"1994-01-01T00:00:00.000Z\",\"1994-02-01T00:00:00.000Z\",\"1994-03-01T00:00:00.000Z\",\"1994-04-01T00:00:00.000Z\",\"1994-05-01T00:00:00.000Z\",\"1994-06-01T00:00:00.000Z\",\"1994-07-01T00:00:00.000Z\",\"1994-08-01T00:00:00.000Z\",\"1994-09-01T00:00:00.000Z\",\"1994-10-01T00:00:00.000Z\",\"1994-11-01T00:00:00.000Z\",\"1994-12-01T00:00:00.000Z\",\"1995-01-01T00:00:00.000Z\",\"1995-02-01T00:00:00.000Z\",\"1995-03-01T00:00:00.000Z\",\"1995-04-01T00:00:00.000Z\",\"1995-05-01T00:00:00.000Z\",\"1995-06-01T00:00:00.000Z\",\"1995-07-01T00:00:00.000Z\",\"1995-08-01T00:00:00.000Z\",\"1995-09-01T00:00:00.000Z\",\"1995-10-01T00:00:00.000Z\",\"1995-11-01T00:00:00.000Z\",\"1995-12-01T00:00:00.000Z\",\"1996-01-01T00:00:00.000Z\",\"1996-02-01T00:00:00.000Z\",\"1996-03-01T00:00:00.000Z\",\"1996-04-01T00:00:00.000Z\",\"1996-05-01T00:00:00.000Z\",\"1996-06-01T00:00:00.000Z\",\"1996-07-01T00:00:00.000Z\",\"1996-08-01T00:00:00.000Z\",\"1996-09-01T00:00:00.000Z\",\"1996-10-01T00:00:00.000Z\",\"1996-11-01T00:00:00.000Z\",\"1996-12-01T00:00:00.000Z\",\"1997-01-01T00:00:00.000Z\",\"1997-02-01T00:00:00.000Z\",\"1997-03-01T00:00:00.000Z\",\"1997-04-01T00:00:00.000Z\",\"1997-05-01T00:00:00.000Z\",\"1997-06-01T00:00:00.000Z\",\"1997-07-01T00:00:00.000Z\",\"1997-08-01T00:00:00.000Z\",\"1997-09-01T00:00:00.000Z\",\"1997-10-01T00:00:00.000Z\",\"1997-11-01T00:00:00.000Z\",\"1997-12-01T00:00:00.000Z\",\"1998-01-01T00:00:00.000Z\",\"1998-02-01T00:00:00.000Z\",\"1998-03-01T00:00:00.000Z\",\"1998-04-01T00:00:00.000Z\",\"1998-05-01T00:00:00.000Z\",\"1998-06-01T00:00:00.000Z\",\"1998-07-01T00:00:00.000Z\",\"1998-08-01T00:00:00.000Z\",\"1998-09-01T00:00:00.000Z\",\"1998-10-01T00:00:00.000Z\",\"1998-11-01T00:00:00.000Z\",\"1998-12-01T00:00:00.000Z\",\"1999-01-01T00:00:00.000Z\",\"1999-02-01T00:00:00.000Z\",\"1999-03-01T00:00:00.000Z\",\"1999-04-01T00:00:00.000Z\",\"1999-05-01T00:00:00.000Z\",\"1999-06-01T00:00:00.000Z\",\"1999-07-01T00:00:00.000Z\",\"1999-08-01T00:00:00.000Z\",\"1999-09-01T00:00:00.000Z\",\"1999-10-01T00:00:00.000Z\",\"1999-11-01T00:00:00.000Z\",\"1999-12-01T00:00:00.000Z\",\"2000-01-01T00:00:00.000Z\",\"2000-02-01T00:00:00.000Z\",\"2000-03-01T00:00:00.000Z\",\"2000-04-01T00:00:00.000Z\",\"2000-05-01T00:00:00.000Z\",\"2000-06-01T00:00:00.000Z\",\"2000-07-01T00:00:00.000Z\",\"2000-08-01T00:00:00.000Z\",\"2000-09-01T00:00:00.000Z\",\"2000-10-01T00:00:00.000Z\",\"2000-11-01T00:00:00.000Z\",\"2000-12-01T00:00:00.000Z\",\"2001-01-01T00:00:00.000Z\",\"2001-02-01T00:00:00.000Z\",\"2001-03-01T00:00:00.000Z\",\"2001-04-01T00:00:00.000Z\",\"2001-05-01T00:00:00.000Z\",\"2001-06-01T00:00:00.000Z\",\"2001-07-01T00:00:00.000Z\",\"2001-08-01T00:00:00.000Z\",\"2001-09-01T00:00:00.000Z\",\"2001-10-01T00:00:00.000Z\",\"2001-11-01T00:00:00.000Z\",\"2001-12-01T00:00:00.000Z\",\"2002-01-01T00:00:00.000Z\",\"2002-02-01T00:00:00.000Z\",\"2002-03-01T00:00:00.000Z\",\"2002-04-01T00:00:00.000Z\",\"2002-05-01T00:00:00.000Z\",\"2002-06-01T00:00:00.000Z\",\"2002-07-01T00:00:00.000Z\",\"2002-08-01T00:00:00.000Z\",\"2002-09-01T00:00:00.000Z\",\"2002-10-01T00:00:00.000Z\",\"2002-11-01T00:00:00.000Z\",\"2002-12-01T00:00:00.000Z\",\"2003-01-01T00:00:00.000Z\",\"2003-02-01T00:00:00.000Z\",\"2003-03-01T00:00:00.000Z\",\"2003-04-01T00:00:00.000Z\",\"2003-05-01T00:00:00.000Z\",\"2003-06-01T00:00:00.000Z\",\"2003-07-01T00:00:00.000Z\",\"2003-08-01T00:00:00.000Z\",\"2003-09-01T00:00:00.000Z\",\"2003-10-01T00:00:00.000Z\",\"2003-11-01T00:00:00.000Z\",\"2003-12-01T00:00:00.000Z\",\"2004-01-01T00:00:00.000Z\",\"2004-02-01T00:00:00.000Z\",\"2004-03-01T00:00:00.000Z\",\"2004-04-01T00:00:00.000Z\",\"2004-05-01T00:00:00.000Z\",\"2004-06-01T00:00:00.000Z\",\"2004-07-01T00:00:00.000Z\",\"2004-08-01T00:00:00.000Z\",\"2004-09-01T00:00:00.000Z\",\"2004-10-01T00:00:00.000Z\",\"2004-11-01T00:00:00.000Z\",\"2004-12-01T00:00:00.000Z\",\"2005-01-01T00:00:00.000Z\",\"2005-02-01T00:00:00.000Z\",\"2005-03-01T00:00:00.000Z\",\"2005-04-01T00:00:00.000Z\",\"2005-05-01T00:00:00.000Z\",\"2005-06-01T00:00:00.000Z\",\"2005-07-01T00:00:00.000Z\",\"2005-08-01T00:00:00.000Z\",\"2005-09-01T00:00:00.000Z\",\"2005-10-01T00:00:00.000Z\",\"2005-11-01T00:00:00.000Z\",\"2005-12-01T00:00:00.000Z\",\"2006-01-01T00:00:00.000Z\",\"2006-02-01T00:00:00.000Z\",\"2006-03-01T00:00:00.000Z\",\"2006-04-01T00:00:00.000Z\",\"2006-05-01T00:00:00.000Z\",\"2006-06-01T00:00:00.000Z\",\"2006-07-01T00:00:00.000Z\",\"2006-08-01T00:00:00.000Z\",\"2006-09-01T00:00:00.000Z\",\"2006-10-01T00:00:00.000Z\",\"2006-11-01T00:00:00.000Z\",\"2006-12-01T00:00:00.000Z\",\"2007-01-01T00:00:00.000Z\",\"2007-02-01T00:00:00.000Z\",\"2007-03-01T00:00:00.000Z\",\"2007-04-01T00:00:00.000Z\",\"2007-05-01T00:00:00.000Z\",\"2007-06-01T00:00:00.000Z\",\"2007-07-01T00:00:00.000Z\",\"2007-08-01T00:00:00.000Z\",\"2007-09-01T00:00:00.000Z\",\"2007-10-01T00:00:00.000Z\",\"2007-11-01T00:00:00.000Z\",\"2007-12-01T00:00:00.000Z\",\"2008-01-01T00:00:00.000Z\",\"2008-02-01T00:00:00.000Z\",\"2008-03-01T00:00:00.000Z\",\"2008-04-01T00:00:00.000Z\",\"2008-05-01T00:00:00.000Z\",\"2008-06-01T00:00:00.000Z\",\"2008-07-01T00:00:00.000Z\",\"2008-08-01T00:00:00.000Z\",\"2008-09-01T00:00:00.000Z\",\"2008-10-01T00:00:00.000Z\",\"2008-11-01T00:00:00.000Z\",\"2008-12-01T00:00:00.000Z\",\"2009-01-01T00:00:00.000Z\",\"2009-02-01T00:00:00.000Z\",\"2009-03-01T00:00:00.000Z\",\"2009-04-01T00:00:00.000Z\",\"2009-05-01T00:00:00.000Z\",\"2009-06-01T00:00:00.000Z\",\"2009-07-01T00:00:00.000Z\",\"2009-08-01T00:00:00.000Z\",\"2009-09-01T00:00:00.000Z\",\"2009-10-01T00:00:00.000Z\",\"2009-11-01T00:00:00.000Z\",\"2009-12-01T00:00:00.000Z\",\"2010-01-01T00:00:00.000Z\",\"2010-02-01T00:00:00.000Z\",\"2010-03-01T00:00:00.000Z\",\"2010-04-01T00:00:00.000Z\",\"2010-05-01T00:00:00.000Z\",\"2010-06-01T00:00:00.000Z\",\"2010-07-01T00:00:00.000Z\",\"2010-08-01T00:00:00.000Z\",\"2010-09-01T00:00:00.000Z\",\"2010-10-01T00:00:00.000Z\",\"2010-11-01T00:00:00.000Z\",\"2010-12-01T00:00:00.000Z\",\"2011-01-01T00:00:00.000Z\",\"2011-02-01T00:00:00.000Z\",\"2011-03-01T00:00:00.000Z\",\"2011-04-01T00:00:00.000Z\",\"2011-05-01T00:00:00.000Z\",\"2011-06-01T00:00:00.000Z\",\"2011-07-01T00:00:00.000Z\",\"2011-08-01T00:00:00.000Z\",\"2011-09-01T00:00:00.000Z\",\"2011-10-01T00:00:00.000Z\",\"2011-11-01T00:00:00.000Z\",\"2011-12-01T00:00:00.000Z\",\"2012-01-01T00:00:00.000Z\",\"2012-02-01T00:00:00.000Z\",\"2012-03-01T00:00:00.000Z\",\"2012-04-01T00:00:00.000Z\",\"2012-05-01T00:00:00.000Z\",\"2012-06-01T00:00:00.000Z\",\"2012-07-01T00:00:00.000Z\",\"2012-08-01T00:00:00.000Z\",\"2012-09-01T00:00:00.000Z\",\"2012-10-01T00:00:00.000Z\",\"2012-11-01T00:00:00.000Z\",\"2012-12-01T00:00:00.000Z\",\"2013-01-01T00:00:00.000Z\",\"2013-02-01T00:00:00.000Z\",\"2013-03-01T00:00:00.000Z\",\"2013-04-01T00:00:00.000Z\",\"2013-05-01T00:00:00.000Z\",\"2013-06-01T00:00:00.000Z\",\"2013-07-01T00:00:00.000Z\",\"2013-08-01T00:00:00.000Z\",\"2013-09-01T00:00:00.000Z\",\"2013-10-01T00:00:00.000Z\",\"2013-11-01T00:00:00.000Z\",\"2013-12-01T00:00:00.000Z\",\"2014-01-01T00:00:00.000Z\",\"2014-02-01T00:00:00.000Z\",\"2014-03-01T00:00:00.000Z\",\"2014-04-01T00:00:00.000Z\",\"2014-05-01T00:00:00.000Z\",\"2014-06-01T00:00:00.000Z\",\"2014-07-01T00:00:00.000Z\",\"2014-08-01T00:00:00.000Z\",\"2014-09-01T00:00:00.000Z\",\"2014-10-01T00:00:00.000Z\",\"2014-11-01T00:00:00.000Z\",\"2014-12-01T00:00:00.000Z\",\"2015-01-01T00:00:00.000Z\",\"2015-02-01T00:00:00.000Z\",\"2015-03-01T00:00:00.000Z\",\"2015-04-01T00:00:00.000Z\",\"2015-05-01T00:00:00.000Z\",\"2015-06-01T00:00:00.000Z\",\"2015-07-01T00:00:00.000Z\",\"2015-08-01T00:00:00.000Z\",\"2015-09-01T00:00:00.000Z\",\"2015-10-01T00:00:00.000Z\",\"2015-11-01T00:00:00.000Z\",\"2015-12-01T00:00:00.000Z\",\"2016-01-01T00:00:00.000Z\",\"2016-02-01T00:00:00.000Z\",\"2016-03-01T00:00:00.000Z\",\"2016-04-01T00:00:00.000Z\",\"2016-05-01T00:00:00.000Z\",\"2016-06-01T00:00:00.000Z\",\"2016-07-01T00:00:00.000Z\",\"2016-08-01T00:00:00.000Z\",\"2016-09-01T00:00:00.000Z\",\"2016-10-01T00:00:00.000Z\",\"2016-11-01T00:00:00.000Z\",\"2016-12-01T00:00:00.000Z\",\"2017-01-01T00:00:00.000Z\",\"2017-02-01T00:00:00.000Z\",\"2017-03-01T00:00:00.000Z\",\"2017-04-01T00:00:00.000Z\",\"2017-05-01T00:00:00.000Z\",\"2017-06-01T00:00:00.000Z\",\"2017-07-01T00:00:00.000Z\",\"2017-08-01T00:00:00.000Z\",\"2017-09-01T00:00:00.000Z\",\"2017-10-01T00:00:00.000Z\",\"2017-11-01T00:00:00.000Z\",\"2017-12-01T00:00:00.000Z\",\"2018-01-01T00:00:00.000Z\",\"2018-02-01T00:00:00.000Z\",\"2018-03-01T00:00:00.000Z\",\"2018-04-01T00:00:00.000Z\",\"2018-05-01T00:00:00.000Z\",\"2018-06-01T00:00:00.000Z\",\"2018-07-01T00:00:00.000Z\",\"2018-08-01T00:00:00.000Z\",\"2018-09-01T00:00:00.000Z\",\"2018-10-01T00:00:00.000Z\",\"2018-11-01T00:00:00.000Z\",\"2018-12-01T00:00:00.000Z\",\"2019-01-01T00:00:00.000Z\",\"2019-02-01T00:00:00.000Z\",\"2019-03-01T00:00:00.000Z\",\"2019-04-01T00:00:00.000Z\",\"2019-05-01T00:00:00.000Z\",\"2019-06-01T00:00:00.000Z\",\"2019-07-01T00:00:00.000Z\",\"2019-08-01T00:00:00.000Z\",\"2019-09-01T00:00:00.000Z\",\"2019-10-01T00:00:00.000Z\",\"2019-11-01T00:00:00.000Z\",\"2019-12-01T00:00:00.000Z\",\"2020-01-01T00:00:00.000Z\",\"2020-02-01T00:00:00.000Z\",\"2020-03-01T00:00:00.000Z\",\"2020-04-01T00:00:00.000Z\",\"2020-05-01T00:00:00.000Z\",\"2020-06-01T00:00:00.000Z\",\"2020-07-01T00:00:00.000Z\",\"2020-08-01T00:00:00.000Z\",\"2020-09-01T00:00:00.000Z\",\"2020-10-01T00:00:00.000Z\",\"2020-11-01T00:00:00.000Z\",\"2020-12-01T00:00:00.000Z\",\"2021-01-01T00:00:00.000Z\",\"2021-02-01T00:00:00.000Z\",\"2021-03-01T00:00:00.000Z\",\"2021-04-01T00:00:00.000Z\",\"2021-05-01T00:00:00.000Z\",\"2021-06-01T00:00:00.000Z\",\"2021-07-01T00:00:00.000Z\",\"2021-08-01T00:00:00.000Z\",\"2021-09-01T00:00:00.000Z\",\"2021-10-01T00:00:00.000Z\",\"2021-11-01T00:00:00.000Z\",\"2021-12-01T00:00:00.000Z\"],[[\"1992-01-01\",\"1992-01-01\",\"1992-01-01\"],[\"1992-02-01\",\"1992-02-01\",\"1992-02-01\"],[\"1992-03-01\",\"1992-03-01\",\"1992-03-01\"],[\"1992-04-01\",\"1992-04-01\",\"1992-04-01\"],[\"1992-05-01\",\"1992-05-01\",\"1992-05-01\"],[\"1992-06-01\",\"1992-06-01\",\"1992-06-01\"],[\"1992-07-01\",\"1992-07-01\",\"1992-07-01\"],[\"1992-08-01\",\"1992-08-01\",\"1992-08-01\"],[\"1992-09-01\",\"1992-09-01\",\"1992-09-01\"],[\"1992-10-01\",\"1992-10-01\",\"1992-10-01\"],[\"1992-11-01\",\"1992-11-01\",\"1992-11-01\"],[\"1992-12-01\",\"1992-12-01\",\"1992-12-01\"],[\"1993-01-01\",\"1993-01-01\",\"1993-01-01\"],[\"1993-02-01\",\"1993-02-01\",\"1993-02-01\"],[\"1993-03-01\",\"1993-03-01\",\"1993-03-01\"],[\"1993-04-01\",\"1993-04-01\",\"1993-04-01\"],[\"1993-05-01\",\"1993-05-01\",\"1993-05-01\"],[\"1993-06-01\",\"1993-06-01\",\"1993-06-01\"],[\"1993-07-01\",\"1993-07-01\",\"1993-07-01\"],[\"1993-08-01\",\"1993-08-01\",\"1993-08-01\"],[\"1993-09-01\",\"1993-09-01\",\"1993-09-01\"],[\"1993-10-01\",\"1993-10-01\",\"1993-10-01\"],[\"1993-11-01\",\"1993-11-01\",\"1993-11-01\"],[\"1993-12-01\",\"1993-12-01\",\"1993-12-01\"],[\"1994-01-01\",\"1994-01-01\",\"1994-01-01\"],[\"1994-02-01\",\"1994-02-01\",\"1994-02-01\"],[\"1994-03-01\",\"1994-03-01\",\"1994-03-01\"],[\"1994-04-01\",\"1994-04-01\",\"1994-04-01\"],[\"1994-05-01\",\"1994-05-01\",\"1994-05-01\"],[\"1994-06-01\",\"1994-06-01\",\"1994-06-01\"],[\"1994-07-01\",\"1994-07-01\",\"1994-07-01\"],[\"1994-08-01\",\"1994-08-01\",\"1994-08-01\"],[\"1994-09-01\",\"1994-09-01\",\"1994-09-01\"],[\"1994-10-01\",\"1994-10-01\",\"1994-10-01\"],[\"1994-11-01\",\"1994-11-01\",\"1994-11-01\"],[\"1994-12-01\",\"1994-12-01\",\"1994-12-01\"],[\"1995-01-01\",\"1995-01-01\",\"1995-01-01\"],[\"1995-02-01\",\"1995-02-01\",\"1995-02-01\"],[\"1995-03-01\",\"1995-03-01\",\"1995-03-01\"],[\"1995-04-01\",\"1995-04-01\",\"1995-04-01\"],[\"1995-05-01\",\"1995-05-01\",\"1995-05-01\"],[\"1995-06-01\",\"1995-06-01\",\"1995-06-01\"],[\"1995-07-01\",\"1995-07-01\",\"1995-07-01\"],[\"1995-08-01\",\"1995-08-01\",\"1995-08-01\"],[\"1995-09-01\",\"1995-09-01\",\"1995-09-01\"],[\"1995-10-01\",\"1995-10-01\",\"1995-10-01\"],[\"1995-11-01\",\"1995-11-01\",\"1995-11-01\"],[\"1995-12-01\",\"1995-12-01\",\"1995-12-01\"],[\"1996-01-01\",\"1996-01-01\",\"1996-01-01\"],[\"1996-02-01\",\"1996-02-01\",\"1996-02-01\"],[\"1996-03-01\",\"1996-03-01\",\"1996-03-01\"],[\"1996-04-01\",\"1996-04-01\",\"1996-04-01\"],[\"1996-05-01\",\"1996-05-01\",\"1996-05-01\"],[\"1996-06-01\",\"1996-06-01\",\"1996-06-01\"],[\"1996-07-01\",\"1996-07-01\",\"1996-07-01\"],[\"1996-08-01\",\"1996-08-01\",\"1996-08-01\"],[\"1996-09-01\",\"1996-09-01\",\"1996-09-01\"],[\"1996-10-01\",\"1996-10-01\",\"1996-10-01\"],[\"1996-11-01\",\"1996-11-01\",\"1996-11-01\"],[\"1996-12-01\",\"1996-12-01\",\"1996-12-01\"],[\"1997-01-01\",\"1997-01-01\",\"1997-01-01\"],[\"1997-02-01\",\"1997-02-01\",\"1997-02-01\"],[\"1997-03-01\",\"1997-03-01\",\"1997-03-01\"],[\"1997-04-01\",\"1997-04-01\",\"1997-04-01\"],[\"1997-05-01\",\"1997-05-01\",\"1997-05-01\"],[\"1997-06-01\",\"1997-06-01\",\"1997-06-01\"],[\"1997-07-01\",\"1997-07-01\",\"1997-07-01\"],[\"1997-08-01\",\"1997-08-01\",\"1997-08-01\"],[\"1997-09-01\",\"1997-09-01\",\"1997-09-01\"],[\"1997-10-01\",\"1997-10-01\",\"1997-10-01\"],[\"1997-11-01\",\"1997-11-01\",\"1997-11-01\"],[\"1997-12-01\",\"1997-12-01\",\"1997-12-01\"],[\"1998-01-01\",\"1998-01-01\",\"1998-01-01\"],[\"1998-02-01\",\"1998-02-01\",\"1998-02-01\"],[\"1998-03-01\",\"1998-03-01\",\"1998-03-01\"],[\"1998-04-01\",\"1998-04-01\",\"1998-04-01\"],[\"1998-05-01\",\"1998-05-01\",\"1998-05-01\"],[\"1998-06-01\",\"1998-06-01\",\"1998-06-01\"],[\"1998-07-01\",\"1998-07-01\",\"1998-07-01\"],[\"1998-08-01\",\"1998-08-01\",\"1998-08-01\"],[\"1998-09-01\",\"1998-09-01\",\"1998-09-01\"],[\"1998-10-01\",\"1998-10-01\",\"1998-10-01\"],[\"1998-11-01\",\"1998-11-01\",\"1998-11-01\"],[\"1998-12-01\",\"1998-12-01\",\"1998-12-01\"],[\"1999-01-01\",\"1999-01-01\",\"1999-01-01\"],[\"1999-02-01\",\"1999-02-01\",\"1999-02-01\"],[\"1999-03-01\",\"1999-03-01\",\"1999-03-01\"],[\"1999-04-01\",\"1999-04-01\",\"1999-04-01\"],[\"1999-05-01\",\"1999-05-01\",\"1999-05-01\"],[\"1999-06-01\",\"1999-06-01\",\"1999-06-01\"],[\"1999-07-01\",\"1999-07-01\",\"1999-07-01\"],[\"1999-08-01\",\"1999-08-01\",\"1999-08-01\"],[\"1999-09-01\",\"1999-09-01\",\"1999-09-01\"],[\"1999-10-01\",\"1999-10-01\",\"1999-10-01\"],[\"1999-11-01\",\"1999-11-01\",\"1999-11-01\"],[\"1999-12-01\",\"1999-12-01\",\"1999-12-01\"],[\"2000-01-01\",\"2000-01-01\",\"2000-01-01\"],[\"2000-02-01\",\"2000-02-01\",\"2000-02-01\"],[\"2000-03-01\",\"2000-03-01\",\"2000-03-01\"],[\"2000-04-01\",\"2000-04-01\",\"2000-04-01\"],[\"2000-05-01\",\"2000-05-01\",\"2000-05-01\"],[\"2000-06-01\",\"2000-06-01\",\"2000-06-01\"],[\"2000-07-01\",\"2000-07-01\",\"2000-07-01\"],[\"2000-08-01\",\"2000-08-01\",\"2000-08-01\"],[\"2000-09-01\",\"2000-09-01\",\"2000-09-01\"],[\"2000-10-01\",\"2000-10-01\",\"2000-10-01\"],[\"2000-11-01\",\"2000-11-01\",\"2000-11-01\"],[\"2000-12-01\",\"2000-12-01\",\"2000-12-01\"],[\"2001-01-01\",\"2001-01-01\",\"2001-01-01\"],[\"2001-02-01\",\"2001-02-01\",\"2001-02-01\"],[\"2001-03-01\",\"2001-03-01\",\"2001-03-01\"],[\"2001-04-01\",\"2001-04-01\",\"2001-04-01\"],[\"2001-05-01\",\"2001-05-01\",\"2001-05-01\"],[\"2001-06-01\",\"2001-06-01\",\"2001-06-01\"],[\"2001-07-01\",\"2001-07-01\",\"2001-07-01\"],[\"2001-08-01\",\"2001-08-01\",\"2001-08-01\"],[\"2001-09-01\",\"2001-09-01\",\"2001-09-01\"],[\"2001-10-01\",\"2001-10-01\",\"2001-10-01\"],[\"2001-11-01\",\"2001-11-01\",\"2001-11-01\"],[\"2001-12-01\",\"2001-12-01\",\"2001-12-01\"],[\"2002-01-01\",\"2002-01-01\",\"2002-01-01\"],[\"2002-02-01\",\"2002-02-01\",\"2002-02-01\"],[\"2002-03-01\",\"2002-03-01\",\"2002-03-01\"],[\"2002-04-01\",\"2002-04-01\",\"2002-04-01\"],[\"2002-05-01\",\"2002-05-01\",\"2002-05-01\"],[\"2002-06-01\",\"2002-06-01\",\"2002-06-01\"],[\"2002-07-01\",\"2002-07-01\",\"2002-07-01\"],[\"2002-08-01\",\"2002-08-01\",\"2002-08-01\"],[\"2002-09-01\",\"2002-09-01\",\"2002-09-01\"],[\"2002-10-01\",\"2002-10-01\",\"2002-10-01\"],[\"2002-11-01\",\"2002-11-01\",\"2002-11-01\"],[\"2002-12-01\",\"2002-12-01\",\"2002-12-01\"],[\"2003-01-01\",\"2003-01-01\",\"2003-01-01\"],[\"2003-02-01\",\"2003-02-01\",\"2003-02-01\"],[\"2003-03-01\",\"2003-03-01\",\"2003-03-01\"],[\"2003-04-01\",\"2003-04-01\",\"2003-04-01\"],[\"2003-05-01\",\"2003-05-01\",\"2003-05-01\"],[\"2003-06-01\",\"2003-06-01\",\"2003-06-01\"],[\"2003-07-01\",\"2003-07-01\",\"2003-07-01\"],[\"2003-08-01\",\"2003-08-01\",\"2003-08-01\"],[\"2003-09-01\",\"2003-09-01\",\"2003-09-01\"],[\"2003-10-01\",\"2003-10-01\",\"2003-10-01\"],[\"2003-11-01\",\"2003-11-01\",\"2003-11-01\"],[\"2003-12-01\",\"2003-12-01\",\"2003-12-01\"],[\"2004-01-01\",\"2004-01-01\",\"2004-01-01\"],[\"2004-02-01\",\"2004-02-01\",\"2004-02-01\"],[\"2004-03-01\",\"2004-03-01\",\"2004-03-01\"],[\"2004-04-01\",\"2004-04-01\",\"2004-04-01\"],[\"2004-05-01\",\"2004-05-01\",\"2004-05-01\"],[\"2004-06-01\",\"2004-06-01\",\"2004-06-01\"],[\"2004-07-01\",\"2004-07-01\",\"2004-07-01\"],[\"2004-08-01\",\"2004-08-01\",\"2004-08-01\"],[\"2004-09-01\",\"2004-09-01\",\"2004-09-01\"],[\"2004-10-01\",\"2004-10-01\",\"2004-10-01\"],[\"2004-11-01\",\"2004-11-01\",\"2004-11-01\"],[\"2004-12-01\",\"2004-12-01\",\"2004-12-01\"],[\"2005-01-01\",\"2005-01-01\",\"2005-01-01\"],[\"2005-02-01\",\"2005-02-01\",\"2005-02-01\"],[\"2005-03-01\",\"2005-03-01\",\"2005-03-01\"],[\"2005-04-01\",\"2005-04-01\",\"2005-04-01\"],[\"2005-05-01\",\"2005-05-01\",\"2005-05-01\"],[\"2005-06-01\",\"2005-06-01\",\"2005-06-01\"],[\"2005-07-01\",\"2005-07-01\",\"2005-07-01\"],[\"2005-08-01\",\"2005-08-01\",\"2005-08-01\"],[\"2005-09-01\",\"2005-09-01\",\"2005-09-01\"],[\"2005-10-01\",\"2005-10-01\",\"2005-10-01\"],[\"2005-11-01\",\"2005-11-01\",\"2005-11-01\"],[\"2005-12-01\",\"2005-12-01\",\"2005-12-01\"],[\"2006-01-01\",\"2006-01-01\",\"2006-01-01\"],[\"2006-02-01\",\"2006-02-01\",\"2006-02-01\"],[\"2006-03-01\",\"2006-03-01\",\"2006-03-01\"],[\"2006-04-01\",\"2006-04-01\",\"2006-04-01\"],[\"2006-05-01\",\"2006-05-01\",\"2006-05-01\"],[\"2006-06-01\",\"2006-06-01\",\"2006-06-01\"],[\"2006-07-01\",\"2006-07-01\",\"2006-07-01\"],[\"2006-08-01\",\"2006-08-01\",\"2006-08-01\"],[\"2006-09-01\",\"2006-09-01\",\"2006-09-01\"],[\"2006-10-01\",\"2006-10-01\",\"2006-10-01\"],[\"2006-11-01\",\"2006-11-01\",\"2006-11-01\"],[\"2006-12-01\",\"2006-12-01\",\"2006-12-01\"],[\"2007-01-01\",\"2007-01-01\",\"2007-01-01\"],[\"2007-02-01\",\"2007-02-01\",\"2007-02-01\"],[\"2007-03-01\",\"2007-03-01\",\"2007-03-01\"],[\"2007-04-01\",\"2007-04-01\",\"2007-04-01\"],[\"2007-05-01\",\"2007-05-01\",\"2007-05-01\"],[\"2007-06-01\",\"2007-06-01\",\"2007-06-01\"],[\"2007-07-01\",\"2007-07-01\",\"2007-07-01\"],[\"2007-08-01\",\"2007-08-01\",\"2007-08-01\"],[\"2007-09-01\",\"2007-09-01\",\"2007-09-01\"],[\"2007-10-01\",\"2007-10-01\",\"2007-10-01\"],[\"2007-11-01\",\"2007-11-01\",\"2007-11-01\"],[\"2007-12-01\",\"2007-12-01\",\"2007-12-01\"],[\"2008-01-01\",\"2008-01-01\",\"2008-01-01\"],[\"2008-02-01\",\"2008-02-01\",\"2008-02-01\"],[\"2008-03-01\",\"2008-03-01\",\"2008-03-01\"],[\"2008-04-01\",\"2008-04-01\",\"2008-04-01\"],[\"2008-05-01\",\"2008-05-01\",\"2008-05-01\"],[\"2008-06-01\",\"2008-06-01\",\"2008-06-01\"],[\"2008-07-01\",\"2008-07-01\",\"2008-07-01\"],[\"2008-08-01\",\"2008-08-01\",\"2008-08-01\"],[\"2008-09-01\",\"2008-09-01\",\"2008-09-01\"],[\"2008-10-01\",\"2008-10-01\",\"2008-10-01\"],[\"2008-11-01\",\"2008-11-01\",\"2008-11-01\"],[\"2008-12-01\",\"2008-12-01\",\"2008-12-01\"],[\"2009-01-01\",\"2009-01-01\",\"2009-01-01\"],[\"2009-02-01\",\"2009-02-01\",\"2009-02-01\"],[\"2009-03-01\",\"2009-03-01\",\"2009-03-01\"],[\"2009-04-01\",\"2009-04-01\",\"2009-04-01\"],[\"2009-05-01\",\"2009-05-01\",\"2009-05-01\"],[\"2009-06-01\",\"2009-06-01\",\"2009-06-01\"],[\"2009-07-01\",\"2009-07-01\",\"2009-07-01\"],[\"2009-08-01\",\"2009-08-01\",\"2009-08-01\"],[\"2009-09-01\",\"2009-09-01\",\"2009-09-01\"],[\"2009-10-01\",\"2009-10-01\",\"2009-10-01\"],[\"2009-11-01\",\"2009-11-01\",\"2009-11-01\"],[\"2009-12-01\",\"2009-12-01\",\"2009-12-01\"],[\"2010-01-01\",\"2010-01-01\",\"2010-01-01\"],[\"2010-02-01\",\"2010-02-01\",\"2010-02-01\"],[\"2010-03-01\",\"2010-03-01\",\"2010-03-01\"],[\"2010-04-01\",\"2010-04-01\",\"2010-04-01\"],[\"2010-05-01\",\"2010-05-01\",\"2010-05-01\"],[\"2010-06-01\",\"2010-06-01\",\"2010-06-01\"],[\"2010-07-01\",\"2010-07-01\",\"2010-07-01\"],[\"2010-08-01\",\"2010-08-01\",\"2010-08-01\"],[\"2010-09-01\",\"2010-09-01\",\"2010-09-01\"],[\"2010-10-01\",\"2010-10-01\",\"2010-10-01\"],[\"2010-11-01\",\"2010-11-01\",\"2010-11-01\"],[\"2010-12-01\",\"2010-12-01\",\"2010-12-01\"],[\"2011-01-01\",\"2011-01-01\",\"2011-01-01\"],[\"2011-02-01\",\"2011-02-01\",\"2011-02-01\"],[\"2011-03-01\",\"2011-03-01\",\"2011-03-01\"],[\"2011-04-01\",\"2011-04-01\",\"2011-04-01\"],[\"2011-05-01\",\"2011-05-01\",\"2011-05-01\"],[\"2011-06-01\",\"2011-06-01\",\"2011-06-01\"],[\"2011-07-01\",\"2011-07-01\",\"2011-07-01\"],[\"2011-08-01\",\"2011-08-01\",\"2011-08-01\"],[\"2011-09-01\",\"2011-09-01\",\"2011-09-01\"],[\"2011-10-01\",\"2011-10-01\",\"2011-10-01\"],[\"2011-11-01\",\"2011-11-01\",\"2011-11-01\"],[\"2011-12-01\",\"2011-12-01\",\"2011-12-01\"],[\"2012-01-01\",\"2012-01-01\",\"2012-01-01\"],[\"2012-02-01\",\"2012-02-01\",\"2012-02-01\"],[\"2012-03-01\",\"2012-03-01\",\"2012-03-01\"],[\"2012-04-01\",\"2012-04-01\",\"2012-04-01\"],[\"2012-05-01\",\"2012-05-01\",\"2012-05-01\"],[\"2012-06-01\",\"2012-06-01\",\"2012-06-01\"],[\"2012-07-01\",\"2012-07-01\",\"2012-07-01\"],[\"2012-08-01\",\"2012-08-01\",\"2012-08-01\"],[\"2012-09-01\",\"2012-09-01\",\"2012-09-01\"],[\"2012-10-01\",\"2012-10-01\",\"2012-10-01\"],[\"2012-11-01\",\"2012-11-01\",\"2012-11-01\"],[\"2012-12-01\",\"2012-12-01\",\"2012-12-01\"],[\"2013-01-01\",\"2013-01-01\",\"2013-01-01\"],[\"2013-02-01\",\"2013-02-01\",\"2013-02-01\"],[\"2013-03-01\",\"2013-03-01\",\"2013-03-01\"],[\"2013-04-01\",\"2013-04-01\",\"2013-04-01\"],[\"2013-05-01\",\"2013-05-01\",\"2013-05-01\"],[\"2013-06-01\",\"2013-06-01\",\"2013-06-01\"],[\"2013-07-01\",\"2013-07-01\",\"2013-07-01\"],[\"2013-08-01\",\"2013-08-01\",\"2013-08-01\"],[\"2013-09-01\",\"2013-09-01\",\"2013-09-01\"],[\"2013-10-01\",\"2013-10-01\",\"2013-10-01\"],[\"2013-11-01\",\"2013-11-01\",\"2013-11-01\"],[\"2013-12-01\",\"2013-12-01\",\"2013-12-01\"],[\"2014-01-01\",\"2014-01-01\",\"2014-01-01\"],[\"2014-02-01\",\"2014-02-01\",\"2014-02-01\"],[\"2014-03-01\",\"2014-03-01\",\"2014-03-01\"],[\"2014-04-01\",\"2014-04-01\",\"2014-04-01\"],[\"2014-05-01\",\"2014-05-01\",\"2014-05-01\"],[\"2014-06-01\",\"2014-06-01\",\"2014-06-01\"],[\"2014-07-01\",\"2014-07-01\",\"2014-07-01\"],[\"2014-08-01\",\"2014-08-01\",\"2014-08-01\"],[\"2014-09-01\",\"2014-09-01\",\"2014-09-01\"],[\"2014-10-01\",\"2014-10-01\",\"2014-10-01\"],[\"2014-11-01\",\"2014-11-01\",\"2014-11-01\"],[\"2014-12-01\",\"2014-12-01\",\"2014-12-01\"],[\"2015-01-01\",\"2015-01-01\",\"2015-01-01\"],[\"2015-02-01\",\"2015-02-01\",\"2015-02-01\"],[\"2015-03-01\",\"2015-03-01\",\"2015-03-01\"],[\"2015-04-01\",\"2015-04-01\",\"2015-04-01\"],[\"2015-05-01\",\"2015-05-01\",\"2015-05-01\"],[\"2015-06-01\",\"2015-06-01\",\"2015-06-01\"],[\"2015-07-01\",\"2015-07-01\",\"2015-07-01\"],[\"2015-08-01\",\"2015-08-01\",\"2015-08-01\"],[\"2015-09-01\",\"2015-09-01\",\"2015-09-01\"],[\"2015-10-01\",\"2015-10-01\",\"2015-10-01\"],[\"2015-11-01\",\"2015-11-01\",\"2015-11-01\"],[\"2015-12-01\",\"2015-12-01\",\"2015-12-01\"],[\"2016-01-01\",\"2016-01-01\",\"2016-01-01\"],[\"2016-02-01\",\"2016-02-01\",\"2016-02-01\"],[\"2016-03-01\",\"2016-03-01\",\"2016-03-01\"],[\"2016-04-01\",\"2016-04-01\",\"2016-04-01\"],[\"2016-05-01\",\"2016-05-01\",\"2016-05-01\"],[\"2016-06-01\",\"2016-06-01\",\"2016-06-01\"],[\"2016-07-01\",\"2016-07-01\",\"2016-07-01\"],[\"2016-08-01\",\"2016-08-01\",\"2016-08-01\"],[\"2016-09-01\",\"2016-09-01\",\"2016-09-01\"],[\"2016-10-01\",\"2016-10-01\",\"2016-10-01\"],[\"2016-11-01\",\"2016-11-01\",\"2016-11-01\"],[\"2016-12-01\",\"2016-12-01\",\"2016-12-01\"],[\"2017-01-01\",\"2017-01-01\",\"2017-01-01\"],[\"2017-02-01\",\"2017-02-01\",\"2017-02-01\"],[\"2017-03-01\",\"2017-03-01\",\"2017-03-01\"],[\"2017-04-01\",\"2017-04-01\",\"2017-04-01\"],[\"2017-05-01\",\"2017-05-01\",\"2017-05-01\"],[\"2017-06-01\",\"2017-06-01\",\"2017-06-01\"],[\"2017-07-01\",\"2017-07-01\",\"2017-07-01\"],[\"2017-08-01\",\"2017-08-01\",\"2017-08-01\"],[\"2017-09-01\",\"2017-09-01\",\"2017-09-01\"],[\"2017-10-01\",\"2017-10-01\",\"2017-10-01\"],[\"2017-11-01\",\"2017-11-01\",\"2017-11-01\"],[\"2017-12-01\",\"2017-12-01\",\"2017-12-01\"],[\"2018-01-01\",\"2018-01-01\",\"2018-01-01\"],[\"2018-02-01\",\"2018-02-01\",\"2018-02-01\"],[\"2018-03-01\",\"2018-03-01\",\"2018-03-01\"],[\"2018-04-01\",\"2018-04-01\",\"2018-04-01\"],[\"2018-05-01\",\"2018-05-01\",\"2018-05-01\"],[\"2018-06-01\",\"2018-06-01\",\"2018-06-01\"],[\"2018-07-01\",\"2018-07-01\",\"2018-07-01\"],[\"2018-08-01\",\"2018-08-01\",\"2018-08-01\"],[\"2018-09-01\",\"2018-09-01\",\"2018-09-01\"],[\"2018-10-01\",\"2018-10-01\",\"2018-10-01\"],[\"2018-11-01\",\"2018-11-01\",\"2018-11-01\"],[\"2018-12-01\",\"2018-12-01\",\"2018-12-01\"],[\"2019-01-01\",\"2019-01-01\",\"2019-01-01\"],[\"2019-02-01\",\"2019-02-01\",\"2019-02-01\"],[\"2019-03-01\",\"2019-03-01\",\"2019-03-01\"],[\"2019-04-01\",\"2019-04-01\",\"2019-04-01\"],[\"2019-05-01\",\"2019-05-01\",\"2019-05-01\"],[\"2019-06-01\",\"2019-06-01\",\"2019-06-01\"],[\"2019-07-01\",\"2019-07-01\",\"2019-07-01\"],[\"2019-08-01\",\"2019-08-01\",\"2019-08-01\"],[\"2019-09-01\",\"2019-09-01\",\"2019-09-01\"],[\"2019-10-01\",\"2019-10-01\",\"2019-10-01\"],[\"2019-11-01\",\"2019-11-01\",\"2019-11-01\"],[\"2019-12-01\",\"2019-12-01\",\"2019-12-01\"],[\"2020-01-01\",\"2020-01-01\",\"2020-01-01\"],[\"2020-02-01\",\"2020-02-01\",\"2020-02-01\"],[\"2020-03-01\",\"2020-03-01\",\"2020-03-01\"],[\"2020-04-01\",\"2020-04-01\",\"2020-04-01\"],[\"2020-05-01\",\"2020-05-01\",\"2020-05-01\"],[\"2020-06-01\",\"2020-06-01\",\"2020-06-01\"],[\"2020-07-01\",\"2020-07-01\",\"2020-07-01\"],[\"2020-08-01\",\"2020-08-01\",\"2020-08-01\"],[\"2020-09-01\",\"2020-09-01\",\"2020-09-01\"],[\"2020-10-01\",\"2020-10-01\",\"2020-10-01\"],[\"2020-11-01\",\"2020-11-01\",\"2020-11-01\"],[\"2020-12-01\",\"2020-12-01\",\"2020-12-01\"],[\"2021-01-01\",\"2021-01-01\",\"2021-01-01\"],[\"2021-02-01\",\"2021-02-01\",\"2021-02-01\"],[\"2021-03-01\",\"2021-03-01\",\"2021-03-01\"],[\"2021-04-01\",\"2021-04-01\",\"2021-04-01\"],[\"2021-05-01\",\"2021-05-01\",\"2021-05-01\"],[\"2021-06-01\",\"2021-06-01\",\"2021-06-01\"],[\"2021-07-01\",\"2021-07-01\",\"2021-07-01\"],[\"2021-08-01\",\"2021-08-01\",\"2021-08-01\"],[\"2021-09-01\",\"2021-09-01\",\"2021-09-01\"],[\"2021-10-01\",\"2021-10-01\",\"2021-10-01\"],[\"2021-11-01\",\"2021-11-01\",\"2021-11-01\"],[\"2021-12-01\",\"2021-12-01\",\"2021-12-01\"]],[[\"23.73526\",\"23.81020\",\"23.88514\"],[\"24.56045\",\"24.64616\",\"24.73187\"],[\"23.40859\",\"23.53628\",\"23.66398\"],[\"22.37523\",\"22.49138\",\"22.60754\"],[\"21.87917\",\"21.98191\",\"22.08465\"],[\"20.08192\",\"20.15395\",\"20.22599\"],[\"18.80270\",\"18.86699\",\"18.93128\"],[\"18.06668\",\"18.15811\",\"18.24953\"],[\"17.93594\",\"18.05717\",\"18.17841\"],[\"19.43518\",\"19.52887\",\"19.62256\"],[\"20.02230\",\"20.10441\",\"20.18652\"],[\"21.89086\",\"22.02957\",\"22.16827\"],[\"24.61270\",\"24.70680\",\"24.80091\"],[\"25.33892\",\"25.38840\",\"25.43789\"],[\"24.34476\",\"24.49581\",\"24.64686\"],[\"22.01463\",\"22.04003\",\"22.06542\"],[\"21.70331\",\"21.77365\",\"21.84399\"],[\"21.14212\",\"21.28907\",\"21.43603\"],[\"20.75908\",\"20.88947\",\"21.01986\"],[\"20.28164\",\"20.39323\",\"20.50483\"],[\"19.42119\",\"19.53082\",\"19.64044\"],[\"19.43595\",\"19.54567\",\"19.65538\"],[\"20.06251\",\"20.18597\",\"20.30943\"],[\"21.74991\",\"21.93701\",\"22.12411\"],[\"23.95001\",\"24.12563\",\"24.30125\"],[\"24.10283\",\"24.19517\",\"24.28751\"],[\"23.22849\",\"23.30113\",\"23.37378\"],[\"22.03761\",\"22.10324\",\"22.16887\"],[\"21.57468\",\"21.68926\",\"21.80384\"],[\"20.33507\",\"20.42128\",\"20.50749\"],[\"19.28576\",\"19.39530\",\"19.50484\"],[\"19.07805\",\"19.24976\",\"19.42146\"],[\"19.35645\",\"19.39387\",\"19.43129\"],[\"19.64244\",\"19.75889\",\"19.87534\"],[\"20.83556\",\"20.98359\",\"21.13161\"],[\"22.88298\",\"22.94323\",\"23.00348\"],[\"23.84159\",\"23.97923\",\"24.11687\"],[\"23.93153\",\"24.05320\",\"24.17486\"],[\"23.59935\",\"23.67184\",\"23.74434\"],[\"22.21074\",\"22.26836\",\"22.32598\"],[\"22.21257\",\"22.31442\",\"22.41628\"],[\"20.26058\",\"20.33085\",\"20.40112\"],[\"18.87342\",\"18.90351\",\"18.93359\"],[\"18.75610\",\"18.86546\",\"18.97483\"],[\"19.10315\",\"19.24587\",\"19.38860\"],[\"19.70263\",\"19.82487\",\"19.94710\"],[\"20.65905\",\"20.73133\",\"20.80361\"],[\"22.85375\",\"22.98715\",\"23.12056\"],[\"24.55998\",\"24.79052\",\"25.02107\"],[\"24.19655\",\"24.31415\",\"24.43175\"],[\"23.16372\",\"23.29586\",\"23.42801\"],[\"22.98665\",\"23.12263\",\"23.25862\"],[\"21.16936\",\"21.28910\",\"21.40884\"],[\"20.44019\",\"20.50637\",\"20.57256\"],[\"19.73133\",\"19.80595\",\"19.88056\"],[\"19.83250\",\"19.89047\",\"19.94845\"],[\"19.68635\",\"19.80497\",\"19.92360\"],[\"19.95040\",\"19.97402\",\"19.99764\"],[\"20.75156\",\"20.86506\",\"20.97856\"],[\"21.54881\",\"21.58272\",\"21.61663\"],[\"22.61956\",\"22.72875\",\"22.83795\"],[\"23.48265\",\"23.53225\",\"23.58184\"],[\"23.64318\",\"23.82442\",\"24.00567\"],[\"23.05633\",\"23.07745\",\"23.09856\"],[\"22.20323\",\"22.27415\",\"22.34507\"],[\"20.94815\",\"20.99424\",\"21.04034\"],[\"20.08231\",\"20.12711\",\"20.17192\"],[\"19.35231\",\"19.37871\",\"19.40511\"],[\"19.19863\",\"19.23666\",\"19.27468\"],[\"19.47173\",\"19.49486\",\"19.51799\"],[\"20.92861\",\"20.99707\",\"21.06553\"],[\"23.09072\",\"23.11468\",\"23.13864\"],[\"24.79180\",\"24.83931\",\"24.88682\"],[\"25.50435\",\"25.65732\",\"25.81029\"],[\"24.63116\",\"24.72654\",\"24.82191\"],[\"23.65209\",\"23.70260\",\"23.75311\"],[\"22.27638\",\"22.36246\",\"22.44855\"],[\"22.12354\",\"22.21401\",\"22.30449\"],[\"19.65639\",\"19.83096\",\"20.00552\"],[\"19.05802\",\"19.22820\",\"19.39837\"],[\"19.71962\",\"19.88639\",\"20.05316\"],[\"20.45607\",\"20.61540\",\"20.77473\"],[\"20.11808\",\"20.25248\",\"20.38688\"],[\"21.81032\",\"21.93036\",\"22.05039\"],[\"24.27739\",\"24.41686\",\"24.55634\"],[\"24.15658\",\"24.20725\",\"24.25792\"],[\"24.69658\",\"24.79227\",\"24.88796\"],[\"23.46504\",\"23.58299\",\"23.70095\"],[\"21.79488\",\"21.87135\",\"21.94782\"],[\"20.45500\",\"20.48844\",\"20.52187\"],[\"18.85476\",\"18.89478\",\"18.93481\"],[\"18.24469\",\"18.33629\",\"18.42789\"],[\"19.58342\",\"19.66847\",\"19.75352\"],[\"20.28729\",\"20.31804\",\"20.34879\"],[\"20.52811\",\"20.55174\",\"20.57537\"],[\"21.41940\",\"21.49140\",\"21.56340\"],[\"22.44508\",\"22.54827\",\"22.65146\"],[\"23.23779\",\"23.32527\",\"23.41275\"],[\"23.30428\",\"23.37036\",\"23.43645\"],[\"22.81613\",\"22.85753\",\"22.89894\"],[\"21.48702\",\"21.58353\",\"21.68004\"],[\"19.71365\",\"19.77621\",\"19.83877\"],[\"18.63441\",\"18.72910\",\"18.82380\"],[\"18.69686\",\"18.77486\",\"18.85286\"],[\"18.90857\",\"18.96795\",\"19.02733\"],[\"19.70540\",\"19.76108\",\"19.81676\"],[\"20.92606\",\"21.00463\",\"21.08320\"],[\"22.58879\",\"22.67505\",\"22.76130\"],[\"23.46883\",\"23.50733\",\"23.54583\"],[\"23.97971\",\"24.04733\",\"24.11494\"],[\"23.79643\",\"23.86566\",\"23.93489\"],[\"22.48544\",\"22.62399\",\"22.76253\"],[\"21.45646\",\"21.58214\",\"21.70782\"],[\"20.01220\",\"20.15738\",\"20.30255\"],[\"19.28775\",\"19.32645\",\"19.36515\"],[\"18.83725\",\"18.88281\",\"18.92838\"],[\"18.84118\",\"18.88057\",\"18.91996\"],[\"19.58148\",\"19.65368\",\"19.72588\"],[\"20.33895\",\"20.47691\",\"20.61486\"],[\"22.06612\",\"22.20954\",\"22.35295\"],[\"23.12953\",\"23.32230\",\"23.51507\"],[\"23.94432\",\"24.03539\",\"24.12646\"],[\"23.76264\",\"23.89405\",\"24.02547\"],[\"22.49825\",\"22.55144\",\"22.60462\"],[\"21.69773\",\"21.74724\",\"21.79675\"],[\"20.41844\",\"20.47670\",\"20.53496\"],[\"18.57388\",\"18.69142\",\"18.80897\"],[\"18.50665\",\"18.55132\",\"18.59598\"],[\"18.72292\",\"18.81002\",\"18.89711\"],[\"19.48442\",\"19.62721\",\"19.77000\"],[\"20.79466\",\"20.93168\",\"21.06870\"],[\"22.60716\",\"22.70662\",\"22.80608\"],[\"23.16299\",\"23.25214\",\"23.34129\"],[\"24.10745\",\"24.16322\",\"24.21898\"],[\"23.53418\",\"23.57313\",\"23.61208\"],[\"22.83045\",\"22.91747\",\"23.00449\"],[\"21.93934\",\"22.01087\",\"22.08239\"],[\"21.99008\",\"22.04675\",\"22.10342\"],[\"19.08160\",\"19.30546\",\"19.52932\"],[\"17.97665\",\"18.18331\",\"18.38997\"],[\"18.87973\",\"18.93872\",\"18.99772\"],[\"19.32513\",\"19.38288\",\"19.44063\"],[\"20.39727\",\"20.45960\",\"20.52193\"],[\"22.21262\",\"22.30515\",\"22.39769\"],[\"23.75803\",\"23.81154\",\"23.86505\"],[\"25.27657\",\"25.34933\",\"25.42208\"],[\"24.02515\",\"24.03989\",\"24.05464\"],[\"23.44482\",\"23.62651\",\"23.80820\"],[\"22.98933\",\"23.09248\",\"23.19563\"],[\"21.33996\",\"21.37376\",\"21.40755\"],[\"20.33158\",\"20.43465\",\"20.53772\"],[\"19.39081\",\"19.54631\",\"19.70181\"],[\"19.09742\",\"19.18047\",\"19.26353\"],[\"20.38061\",\"20.46304\",\"20.54546\"],[\"21.20747\",\"21.25361\",\"21.29975\"],[\"22.90138\",\"23.03348\",\"23.16558\"],[\"23.44045\",\"23.49793\",\"23.55542\"],[\"24.39264\",\"24.44548\",\"24.49832\"],[\"24.28272\",\"24.31584\",\"24.34896\"],[\"23.40596\",\"23.49275\",\"23.57955\"],[\"22.55998\",\"22.64370\",\"22.72743\"],[\"21.14346\",\"21.19501\",\"21.24657\"],[\"20.58214\",\"20.66183\",\"20.74152\"],[\"19.26901\",\"19.44831\",\"19.62760\"],[\"19.15486\",\"19.21862\",\"19.28238\"],[\"20.17337\",\"20.24054\",\"20.30771\"],[\"20.90951\",\"20.93634\",\"20.96318\"],[\"22.54700\",\"22.68065\",\"22.81430\"],[\"24.16689\",\"24.23325\",\"24.29961\"],[\"24.85533\",\"24.91709\",\"24.97885\"],[\"24.30300\",\"24.39611\",\"24.48922\"],[\"22.91311\",\"22.97471\",\"23.03632\"],[\"21.37321\",\"21.40736\",\"21.44151\"],[\"20.14013\",\"20.17021\",\"20.20029\"],[\"18.79081\",\"18.81907\",\"18.84732\"],[\"18.73689\",\"18.79517\",\"18.85345\"],[\"19.22169\",\"19.31572\",\"19.40975\"],[\"19.23724\",\"19.28794\",\"19.33865\"],[\"20.57203\",\"20.67527\",\"20.77851\"],[\"21.62773\",\"21.68973\",\"21.75173\"],[\"23.00999\",\"23.08447\",\"23.15895\"],[\"23.82111\",\"23.86055\",\"23.90000\"],[\"23.73015\",\"23.79379\",\"23.85744\"],[\"22.78175\",\"22.81373\",\"22.84572\"],[\"22.21935\",\"22.32266\",\"22.42597\"],[\"21.06232\",\"21.11218\",\"21.16204\"],[\"19.54734\",\"19.56679\",\"19.58624\"],[\"19.01764\",\"19.04185\",\"19.06606\"],[\"18.83700\",\"18.90030\",\"18.96360\"],[\"19.53429\",\"19.62030\",\"19.70632\"],[\"21.64358\",\"21.70679\",\"21.77000\"],[\"23.56967\",\"23.64569\",\"23.72172\"],[\"24.08155\",\"24.22241\",\"24.36327\"],[\"24.33100\",\"24.40943\",\"24.48785\"],[\"23.64978\",\"23.67731\",\"23.70484\"],[\"22.80597\",\"22.84013\",\"22.87428\"],[\"21.16269\",\"21.20212\",\"21.24156\"],[\"20.21685\",\"20.23416\",\"20.25147\"],[\"19.61473\",\"19.63441\",\"19.65409\"],[\"18.89331\",\"18.97528\",\"19.05725\"],[\"18.94479\",\"19.04306\",\"19.14133\"],[\"19.15718\",\"19.26332\",\"19.36946\"],[\"20.45542\",\"20.55849\",\"20.66156\"],[\"21.79493\",\"21.84153\",\"21.88813\"],[\"23.61035\",\"23.66774\",\"23.72513\"],[\"25.15121\",\"25.23558\",\"25.31995\"],[\"25.04795\",\"25.14247\",\"25.23698\"],[\"23.24923\",\"23.31351\",\"23.37778\"],[\"21.06988\",\"21.13928\",\"21.20869\"],[\"20.69240\",\"20.78362\",\"20.87483\"],[\"19.07847\",\"19.16305\",\"19.24763\"],[\"18.83670\",\"18.92590\",\"19.01509\"],[\"19.36631\",\"19.45028\",\"19.53425\"],[\"19.58022\",\"19.82692\",\"20.07362\"],[\"21.76354\",\"21.98283\",\"22.20212\"],[\"23.89796\",\"23.99516\",\"24.09236\"],[\"25.53473\",\"25.63443\",\"25.73413\"],[\"25.56225\",\"25.67318\",\"25.78410\"],[\"25.34885\",\"25.39085\",\"25.43285\"],[\"24.37453\",\"24.40188\",\"24.42923\"],[\"22.23808\",\"22.29668\",\"22.35528\"],[\"20.14865\",\"20.19608\",\"20.24351\"],[\"19.79857\",\"19.84857\",\"19.89857\"],[\"19.89830\",\"19.95969\",\"20.02107\"],[\"19.41558\",\"19.57436\",\"19.73315\"],[\"19.25880\",\"19.32812\",\"19.39744\"],[\"20.22993\",\"20.35415\",\"20.47837\"],[\"23.28580\",\"23.32475\",\"23.36369\"],[\"24.41160\",\"24.46936\",\"24.52711\"],[\"25.39573\",\"25.41793\",\"25.44013\"],[\"24.52360\",\"24.61442\",\"24.70524\"],[\"23.68591\",\"23.74088\",\"23.79585\"],[\"21.97187\",\"22.01281\",\"22.05374\"],[\"20.64942\",\"20.67468\",\"20.69993\"],[\"19.15273\",\"19.22147\",\"19.29021\"],[\"18.95323\",\"18.99389\",\"19.03456\"],[\"19.34714\",\"19.45481\",\"19.56249\"],[\"20.31355\",\"20.44055\",\"20.56755\"],[\"21.91683\",\"21.96375\",\"22.01068\"],[\"22.20714\",\"22.25420\",\"22.30126\"],[\"22.65726\",\"22.79085\",\"22.92444\"],[\"24.51277\",\"24.56986\",\"24.62695\"],[\"23.79990\",\"23.87138\",\"23.94286\"],[\"22.54182\",\"22.65482\",\"22.76782\"],[\"21.23267\",\"21.30439\",\"21.37610\"],[\"20.24003\",\"20.38436\",\"20.52869\"],[\"19.26199\",\"19.28691\",\"19.31183\"],[\"18.10838\",\"18.36340\",\"18.61842\"],[\"18.32846\",\"18.49473\",\"18.66101\"],[\"19.03567\",\"19.08113\",\"19.12659\"],[\"20.84544\",\"20.90219\",\"20.95895\"],[\"22.57227\",\"22.64035\",\"22.70844\"],[\"23.91116\",\"24.07080\",\"24.23043\"],[\"23.67972\",\"23.73244\",\"23.78516\"],[\"23.46757\",\"23.51889\",\"23.57020\"],[\"22.88470\",\"22.92283\",\"22.96095\"],[\"21.99636\",\"22.06980\",\"22.14324\"],[\"20.56851\",\"20.68669\",\"20.80487\"],[\"19.64374\",\"19.71872\",\"19.79369\"],[\"18.99504\",\"19.13457\",\"19.27409\"],[\"19.02358\",\"19.26195\",\"19.50032\"],[\"19.46451\",\"19.52402\",\"19.58352\"],[\"20.72039\",\"20.78242\",\"20.84445\"],[\"22.14796\",\"22.17974\",\"22.21151\"],[\"22.99125\",\"23.05331\",\"23.11537\"],[\"23.85684\",\"23.91047\",\"23.96409\"],[\"23.81327\",\"23.95435\",\"24.09543\"],[\"23.65492\",\"23.78595\",\"23.91697\"],[\"21.74244\",\"21.80790\",\"21.87336\"],[\"21.64314\",\"21.72741\",\"21.81168\"],[\"19.43789\",\"19.57504\",\"19.71219\"],[\"19.34763\",\"19.39481\",\"19.44200\"],[\"18.64329\",\"18.87722\",\"19.11114\"],[\"19.75121\",\"20.00354\",\"20.25588\"],[\"21.24112\",\"21.34402\",\"21.44691\"],[\"22.65011\",\"22.83040\",\"23.01070\"],[\"24.37374\",\"24.48966\",\"24.60558\"],[\"24.05550\",\"24.11332\",\"24.17113\"],[\"24.76782\",\"24.84122\",\"24.91462\"],[\"24.13020\",\"24.14471\",\"24.15922\"],[\"22.44277\",\"22.46222\",\"22.48168\"],[\"21.09746\",\"21.12728\",\"21.15710\"],[\"19.93823\",\"19.96662\",\"19.99501\"],[\"19.36919\",\"19.43003\",\"19.49086\"],[\"19.11715\",\"19.19321\",\"19.26928\"],[\"19.84949\",\"20.00830\",\"20.16711\"],[\"20.13153\",\"20.23051\",\"20.32949\"],[\"22.00379\",\"22.05282\",\"22.10185\"],[\"23.36147\",\"23.43406\",\"23.50666\"],[\"24.22818\",\"24.27169\",\"24.31521\"],[\"24.53159\",\"24.59761\",\"24.66363\"],[\"24.10578\",\"24.22810\",\"24.35042\"],[\"22.98091\",\"23.03043\",\"23.07995\"],[\"20.44682\",\"20.56473\",\"20.68265\"],[\"19.81361\",\"19.88348\",\"19.95335\"],[\"19.67170\",\"19.72589\",\"19.78007\"],[\"19.83753\",\"19.89609\",\"19.95466\"],[\"19.47197\",\"19.54408\",\"19.61619\"],[\"20.93158\",\"21.08389\",\"21.23621\"],[\"22.97369\",\"23.07573\",\"23.17776\"],[\"23.90443\",\"24.03929\",\"24.17415\"],[\"24.69059\",\"24.75982\",\"24.82905\"],[\"23.92328\",\"23.99626\",\"24.06923\"],[\"22.73364\",\"22.82580\",\"22.91796\"],[\"21.20193\",\"21.31387\",\"21.42582\"],[\"19.54735\",\"19.88502\",\"20.22270\"],[\"19.44793\",\"19.52535\",\"19.60276\"],[\"19.12408\",\"19.25738\",\"19.39068\"],[\"19.21051\",\"19.27644\",\"19.34237\"],[\"20.73250\",\"20.88892\",\"21.04533\"],[\"21.56787\",\"21.65967\",\"21.75147\"],[\"23.49235\",\"23.58211\",\"23.67187\"],[\"24.28929\",\"24.33034\",\"24.37138\"],[\"24.05343\",\"24.13223\",\"24.21103\"],[\"24.27682\",\"24.36158\",\"24.44634\"],[\"23.67954\",\"23.75937\",\"23.83921\"],[\"21.64810\",\"21.73323\",\"21.81837\"],[\"19.97520\",\"20.02884\",\"20.08247\"],[\"18.83678\",\"18.90828\",\"18.97977\"],[\"18.67909\",\"18.85846\",\"19.03783\"],[\"19.23476\",\"19.36420\",\"19.49365\"],[\"20.36743\",\"20.56682\",\"20.76620\"],[\"21.09773\",\"21.14156\",\"21.18540\"],[\"22.32748\",\"22.42889\",\"22.53030\"],[\"25.02461\",\"25.07178\",\"25.11894\"],[\"25.15831\",\"25.21909\",\"25.27987\"],[\"24.84659\",\"24.87747\",\"24.90835\"],[\"24.03785\",\"24.10196\",\"24.16608\"],[\"22.93026\",\"22.94799\",\"22.96572\"],[\"21.57795\",\"21.63425\",\"21.69054\"],[\"20.22697\",\"20.28663\",\"20.34628\"],[\"19.70121\",\"19.74460\",\"19.78799\"],[\"19.06586\",\"19.13440\",\"19.20294\"],[\"19.21336\",\"19.24803\",\"19.28271\"],[\"20.82060\",\"20.87000\",\"20.91940\"],[\"22.36779\",\"22.48294\",\"22.59809\"],[\"24.62130\",\"24.69938\",\"24.77746\"],[\"25.06947\",\"25.19886\",\"25.32826\"],[\"24.33454\",\"24.40605\",\"24.47756\"],[\"23.32157\",\"23.38214\",\"23.44271\"],[\"22.08382\",\"22.18001\",\"22.27621\"],[\"21.16210\",\"21.21323\",\"21.26436\"],[\"20.39119\",\"20.49863\",\"20.60607\"],[\"19.56947\",\"19.62281\",\"19.67615\"],[\"19.17441\",\"19.31752\",\"19.46064\"],[\"20.51914\",\"20.64296\",\"20.76678\"],[\"21.88917\",\"21.97201\",\"22.05485\"],[\"22.49908\",\"22.61253\",\"22.72598\"],[\"24.19261\",\"24.28752\",\"24.38243\"],[\"23.57323\",\"23.67143\",\"23.76963\"],[\"22.95659\",\"23.03650\",\"23.11641\"],[\"22.60739\",\"22.69884\",\"22.79029\"],[\"21.24617\",\"21.32460\",\"21.40303\"],[\"19.88391\",\"20.10028\",\"20.31665\"],[\"19.52687\",\"19.61642\",\"19.70596\"],[\"18.98695\",\"19.03696\",\"19.08696\"],[\"18.94865\",\"19.02285\",\"19.09705\"],[\"19.88412\",\"19.97016\",\"20.05619\"],[\"21.09618\",\"21.19351\",\"21.29084\"],[\"23.14864\",\"23.28307\",\"23.41750\"]]],\"fixedtz\":false,\"tzone\":\"UTC\",\"plugins\":{\"Crosshair\":{\"direction\":\"vertical\"}}},\"evals\":[\"attrs.interactionModel\"],\"jsHooks\":[]}</script>\n```\n:::\n:::\n\n\n<br>\nAdd explanation\n\n\n::: {.cell}\n::: {.cell-output-display}\n```{=html}\n<div class=\"dygraphs html-widget html-fill-item\" id=\"htmlwidget-14a8cdf196439e7683d7\" style=\"width:100%;height:464px;\"></div>\n<script type=\"application/json\" data-for=\"htmlwidget-14a8cdf196439e7683d7\">{\"x\":{\"attrs\":{\"axes\":{\"x\":{\"pixelsPerLabel\":60,\"drawAxis\":true},\"y\":{\"drawAxis\":true}},\"series\":{\"Lord Howe Island Group\":{\"axis\":\"y\"}},\"colors\":[\"#3980AB\"],\"title\":\"Mean yearly temperature\",\"labels\":[\"year\",\"date\",\"Lord Howe Island Group\"],\"legend\":\"auto\",\"retainDateWindow\":false,\"customBars\":true,\"stackedGraph\":false,\"fillGraph\":false,\"fillAlpha\":0.1,\"stepPlot\":false,\"drawPoints\":false,\"pointSize\":1,\"drawGapEdgePoints\":false,\"connectSeparatedPoints\":false,\"strokeWidth\":1,\"strokeBorderColor\":\"white\",\"colorValue\":0.5,\"colorSaturation\":1,\"includeZero\":false,\"drawAxesAtZero\":false,\"logscale\":false,\"axisTickSize\":3,\"axisLineColor\":\"black\",\"axisLineWidth\":0.3,\"axisLabelColor\":\"black\",\"axisLabelFontSize\":14,\"axisLabelWidth\":60,\"drawGrid\":false,\"gridLineWidth\":0.3,\"rightGap\":5,\"digitsAfterDecimal\":2,\"labelsKMB\":false,\"labelsKMG2\":false,\"labelsUTC\":true,\"maxNumberWidth\":6,\"animatedZooms\":false,\"mobileDisableYTouch\":true,\"disableZoom\":false,\"ylabel\":\"Temperature (°C)\",\"showRangeSelector\":true,\"rangeSelectorHeight\":40,\"rangeSelectorPlotFillColor\":\"#D6D6D6\",\"rangeSelectorPlotStrokeColor\":\"\",\"interactionModel\":\"Dygraph.Interaction.defaultModel\",\"highlightCircleSize\":5,\"highlightSeriesBackgroundAlpha\":0.2,\"highlightSeriesOpts\":{\"strokeWidth\":2},\"hideOverlayOnMouseOut\":false},\"scale\":\"yearly\",\"group\":\"sst\",\"annotations\":[],\"shadings\":[],\"events\":[],\"format\":\"date\",\"data\":[[\"1992-01-01T00:00:00.000Z\",\"1993-01-01T00:00:00.000Z\",\"1994-01-01T00:00:00.000Z\",\"1995-01-01T00:00:00.000Z\",\"1996-01-01T00:00:00.000Z\",\"1997-01-01T00:00:00.000Z\",\"1998-01-01T00:00:00.000Z\",\"1999-01-01T00:00:00.000Z\",\"2000-01-01T00:00:00.000Z\",\"2001-01-01T00:00:00.000Z\",\"2002-01-01T00:00:00.000Z\",\"2003-01-01T00:00:00.000Z\",\"2004-01-01T00:00:00.000Z\",\"2005-01-01T00:00:00.000Z\",\"2006-01-01T00:00:00.000Z\",\"2007-01-01T00:00:00.000Z\",\"2008-01-01T00:00:00.000Z\",\"2009-01-01T00:00:00.000Z\",\"2010-01-01T00:00:00.000Z\",\"2011-01-01T00:00:00.000Z\",\"2012-01-01T00:00:00.000Z\",\"2013-01-01T00:00:00.000Z\",\"2014-01-01T00:00:00.000Z\",\"2015-01-01T00:00:00.000Z\",\"2016-01-01T00:00:00.000Z\",\"2017-01-01T00:00:00.000Z\",\"2018-01-01T00:00:00.000Z\",\"2019-01-01T00:00:00.000Z\",\"2020-01-01T00:00:00.000Z\",\"2021-01-01T00:00:00.000Z\"],[[\"1992-01-01\",\"1992-01-01\",\"1992-01-01\"],[\"1993-01-01\",\"1993-01-01\",\"1993-01-01\"],[\"1994-01-01\",\"1994-01-01\",\"1994-01-01\"],[\"1995-01-01\",\"1995-01-01\",\"1995-01-01\"],[\"1996-01-01\",\"1996-01-01\",\"1996-01-01\"],[\"1997-01-01\",\"1997-01-01\",\"1997-01-01\"],[\"1998-01-01\",\"1998-01-01\",\"1998-01-01\"],[\"1999-01-01\",\"1999-01-01\",\"1999-01-01\"],[\"2000-01-01\",\"2000-01-01\",\"2000-01-01\"],[\"2001-01-01\",\"2001-01-01\",\"2001-01-01\"],[\"2002-01-01\",\"2002-01-01\",\"2002-01-01\"],[\"2003-01-01\",\"2003-01-01\",\"2003-01-01\"],[\"2004-01-01\",\"2004-01-01\",\"2004-01-01\"],[\"2005-01-01\",\"2005-01-01\",\"2005-01-01\"],[\"2006-01-01\",\"2006-01-01\",\"2006-01-01\"],[\"2007-01-01\",\"2007-01-01\",\"2007-01-01\"],[\"2008-01-01\",\"2008-01-01\",\"2008-01-01\"],[\"2009-01-01\",\"2009-01-01\",\"2009-01-01\"],[\"2010-01-01\",\"2010-01-01\",\"2010-01-01\"],[\"2011-01-01\",\"2011-01-01\",\"2011-01-01\"],[\"2012-01-01\",\"2012-01-01\",\"2012-01-01\"],[\"2013-01-01\",\"2013-01-01\",\"2013-01-01\"],[\"2014-01-01\",\"2014-01-01\",\"2014-01-01\"],[\"2015-01-01\",\"2015-01-01\",\"2015-01-01\"],[\"2016-01-01\",\"2016-01-01\",\"2016-01-01\"],[\"2017-01-01\",\"2017-01-01\",\"2017-01-01\"],[\"2018-01-01\",\"2018-01-01\",\"2018-01-01\"],[\"2019-01-01\",\"2019-01-01\",\"2019-01-01\"],[\"2020-01-01\",\"2020-01-01\",\"2020-01-01\"],[\"2021-01-01\",\"2021-01-01\",\"2021-01-01\"]],[[\"21.01619\",\"21.11375\",\"21.21131\"],[\"21.73889\",\"21.84799\",\"21.95710\"],[\"21.35916\",\"21.46336\",\"21.56756\"],[\"21.33370\",\"21.43134\",\"21.52898\"],[\"21.50145\",\"21.60349\",\"21.70552\"],[\"21.50645\",\"21.56503\",\"21.62361\"],[\"21.98315\",\"22.10384\",\"22.22452\"],[\"21.48026\",\"21.55166\",\"21.62305\"],[\"21.03867\",\"21.11449\",\"21.19030\"],[\"21.17932\",\"21.26782\",\"21.35631\"],[\"21.17838\",\"21.27878\",\"21.37918\"],[\"21.28646\",\"21.37823\",\"21.46999\"],[\"22.01193\",\"22.10042\",\"22.18892\"],[\"21.82176\",\"21.89808\",\"21.97441\"],[\"21.32817\",\"21.39014\",\"21.45210\"],[\"21.56451\",\"21.62243\",\"21.68034\"],[\"21.25902\",\"21.32514\",\"21.39126\"],[\"21.77869\",\"21.88553\",\"21.99237\"],[\"22.09117\",\"22.16523\",\"22.23928\"],[\"21.87740\",\"21.93823\",\"21.99906\"],[\"21.09472\",\"21.19536\",\"21.29601\"],[\"21.37527\",\"21.46690\",\"21.55854\"],[\"21.56443\",\"21.68870\",\"21.81298\"],[\"21.77307\",\"21.83832\",\"21.90358\"],[\"21.86290\",\"21.94465\",\"22.02640\"],[\"21.63137\",\"21.75083\",\"21.87028\"],[\"21.53880\",\"21.63448\",\"21.73016\"],[\"22.08095\",\"22.13493\",\"22.18891\"],[\"22.05294\",\"22.14551\",\"22.23809\"],[\"21.33761\",\"21.43684\",\"21.53608\"]]],\"fixedtz\":false,\"tzone\":\"UTC\",\"plugins\":{\"Crosshair\":{\"direction\":\"vertical\"}}},\"evals\":[\"attrs.interactionModel\"],\"jsHooks\":[]}</script>\n```\n:::\n:::\n\n\n<br>\n\n\n::: {.cell}\n::: {.cell-output-display}\n```{=html}\n<div class=\"dygraphs html-widget html-fill-item\" id=\"htmlwidget-e0f8dedabd17d83e5da2\" style=\"width:100%;height:464px;\"></div>\n<script type=\"application/json\" data-for=\"htmlwidget-e0f8dedabd17d83e5da2\">{\"x\":{\"attrs\":{\"axes\":{\"x\":{\"pixelsPerLabel\":60,\"drawAxis\":true},\"y\":{\"drawAxis\":true,\"valueRange\":[-0.5,1]}},\"series\":{\"Lord Howe Island Group\":{\"axis\":\"y\"}},\"colors\":[\"#3980AB\"],\"title\":\"Yearly temperature anomaly\",\"labels\":[\"year\",\"date\",\"Lord Howe Island Group\"],\"legend\":\"auto\",\"retainDateWindow\":false,\"stackedGraph\":false,\"fillGraph\":false,\"fillAlpha\":0.1,\"stepPlot\":false,\"drawPoints\":false,\"pointSize\":1,\"drawGapEdgePoints\":false,\"connectSeparatedPoints\":false,\"strokeWidth\":1,\"strokeBorderColor\":\"white\",\"colorValue\":0.5,\"colorSaturation\":1,\"includeZero\":false,\"drawAxesAtZero\":false,\"logscale\":false,\"axisTickSize\":3,\"axisLineColor\":\"black\",\"axisLineWidth\":0.3,\"axisLabelColor\":\"black\",\"axisLabelFontSize\":14,\"axisLabelWidth\":60,\"drawGrid\":false,\"gridLineWidth\":0.3,\"rightGap\":5,\"digitsAfterDecimal\":2,\"labelsKMB\":false,\"labelsKMG2\":false,\"labelsUTC\":true,\"maxNumberWidth\":6,\"animatedZooms\":false,\"mobileDisableYTouch\":true,\"disableZoom\":false,\"ylabel\":\"Temperature (°C)\",\"showRangeSelector\":true,\"rangeSelectorHeight\":40,\"rangeSelectorPlotFillColor\":\"#D6D6D6\",\"rangeSelectorPlotStrokeColor\":\"\",\"interactionModel\":\"Dygraph.Interaction.defaultModel\",\"highlightCircleSize\":5,\"highlightSeriesBackgroundAlpha\":0.2,\"highlightSeriesOpts\":{\"strokeWidth\":2},\"hideOverlayOnMouseOut\":false},\"scale\":\"yearly\",\"group\":\"sst\",\"annotations\":[],\"shadings\":[],\"events\":[{\"pos\":0,\"labelLoc\":\"left\",\"color\":\"darkgrey\",\"strokePattern\":[7,3],\"axis\":\"y\"}],\"format\":\"date\",\"data\":[[\"1992-01-01T00:00:00.000Z\",\"1993-01-01T00:00:00.000Z\",\"1994-01-01T00:00:00.000Z\",\"1995-01-01T00:00:00.000Z\",\"1996-01-01T00:00:00.000Z\",\"1997-01-01T00:00:00.000Z\",\"1998-01-01T00:00:00.000Z\",\"1999-01-01T00:00:00.000Z\",\"2000-01-01T00:00:00.000Z\",\"2001-01-01T00:00:00.000Z\",\"2002-01-01T00:00:00.000Z\",\"2003-01-01T00:00:00.000Z\",\"2004-01-01T00:00:00.000Z\",\"2005-01-01T00:00:00.000Z\",\"2006-01-01T00:00:00.000Z\",\"2007-01-01T00:00:00.000Z\",\"2008-01-01T00:00:00.000Z\",\"2009-01-01T00:00:00.000Z\",\"2010-01-01T00:00:00.000Z\",\"2011-01-01T00:00:00.000Z\",\"2012-01-01T00:00:00.000Z\",\"2013-01-01T00:00:00.000Z\",\"2014-01-01T00:00:00.000Z\",\"2015-01-01T00:00:00.000Z\",\"2016-01-01T00:00:00.000Z\",\"2017-01-01T00:00:00.000Z\",\"2018-01-01T00:00:00.000Z\",\"2019-01-01T00:00:00.000Z\",\"2020-01-01T00:00:00.000Z\",\"2021-01-01T00:00:00.000Z\"],[\"1992-01-01\",\"1993-01-01\",\"1994-01-01\",\"1995-01-01\",\"1996-01-01\",\"1997-01-01\",\"1998-01-01\",\"1999-01-01\",\"2000-01-01\",\"2001-01-01\",\"2002-01-01\",\"2003-01-01\",\"2004-01-01\",\"2005-01-01\",\"2006-01-01\",\"2007-01-01\",\"2008-01-01\",\"2009-01-01\",\"2010-01-01\",\"2011-01-01\",\"2012-01-01\",\"2013-01-01\",\"2014-01-01\",\"2015-01-01\",\"2016-01-01\",\"2017-01-01\",\"2018-01-01\",\"2019-01-01\",\"2020-01-01\",\"2021-01-01\"],[\"-0.528966077\",\" 0.205277952\",\"-0.179354636\",\"-0.211375046\",\"-0.039229997\",\"-0.077686914\",\" 0.461118730\",\"-0.091059335\",\"-0.528230000\",\"-0.374901422\",\"-0.363934326\",\"-0.264491367\",\" 0.457705371\",\" 0.255368106\",\"-0.252581247\",\"-0.020290184\",\"-0.317578602\",\" 0.242811235\",\" 0.522512468\",\" 0.295513503\",\"-0.447351583\",\"-0.175813166\",\" 0.045984300\",\" 0.195608330\",\" 0.301933002\",\" 0.108109665\",\"-0.008232721\",\" 0.492211056\",\" 0.502795569\",\"-0.205872663\"]],\"fixedtz\":false,\"tzone\":\"UTC\",\"plugins\":{\"Crosshair\":{\"direction\":\"vertical\"}}},\"evals\":[\"attrs.interactionModel\"],\"jsHooks\":[]}</script>\n```\n:::\n:::\n\n\n\n\n\n## Temperature trends\n\nMann-Kendall test. To be improved!\n\n\n::: {.cell}\n::: {.cell-output-display}\n![](site64217_files/figure-html/unnamed-chunk-7-1.png){width=672}\n:::\n:::\n\n\n## Temperature ranges\n\n\n::: {.cell}\n::: {.cell-output-display}\n| Maximum (period)| Minimum (period)| Mean yearly maximum| SD yearly maximum| Mean yearly minimum| SD yearly minimum|\n|----------------:|----------------:|-------------------:|-----------------:|-------------------:|-----------------:|\n|            32.69|             1.42|                24.6|               0.6|               18.99|               0.4|\n:::\n:::\n",
    "supporting": [
      "site64217_files"
    ],
    "filters": [
      "rmarkdown/pagebreak.lua"
    ],
    "includes": {
      "include-in-header": [
        "<script src=\"../site_libs/htmlwidgets-1.6.4/htmlwidgets.js\"></script>\n<script src=\"../site_libs/jquery-3.6.0/jquery-3.6.0.min.js\"></script>\n<link href=\"../site_libs/leaflet-1.3.1/leaflet.css\" rel=\"stylesheet\" />\n<script src=\"../site_libs/leaflet-1.3.1/leaflet.js\"></script>\n<link href=\"../site_libs/leafletfix-1.0.0/leafletfix.css\" rel=\"stylesheet\" />\n<script src=\"../site_libs/proj4-2.6.2/proj4.min.js\"></script>\n<script src=\"../site_libs/Proj4Leaflet-1.0.1/proj4leaflet.js\"></script>\n<link href=\"../site_libs/rstudio_leaflet-1.3.1/rstudio_leaflet.css\" rel=\"stylesheet\" />\n<script src=\"../site_libs/leaflet-binding-2.2.1/leaflet.js\"></script>\n<link href=\"../site_libs/dygraphs-1.1.1/dygraph.css\" rel=\"stylesheet\" />\n<script src=\"../site_libs/dygraphs-1.1.1/dygraph-combined.js\"></script>\n<script src=\"../site_libs/dygraphs-1.1.1/shapes.js\"></script>\n<script src=\"../site_libs/moment-2.8.4/moment.js\"></script>\n<script src=\"../site_libs/moment-timezone-0.2.5/moment-timezone-with-data.js\"></script>\n<script src=\"../site_libs/moment-fquarter-1.0.0/moment-fquarter.min.js\"></script>\n<script src=\"../site_libs/dygraphs-binding-1.1.1.6/dygraphs.js\"></script>\n<script src=\"../site_libs/Dygraph.Plugins.Crosshair-1.0/crosshair.js\"></script>\n"
      ]
    },
    "engineDependencies": {},
    "preserve": {},
    "postProcess": true
  }
}